thingflow/__init__.py
thingflow/base.py
thingflow/adapters/__init__.py
thingflow/adapters/bokeh.py
thingflow/adapters/csv.py
thingflow/adapters/generic.py
thingflow/adapters/influxdb.py
thingflow/adapters/mqtt.py
thingflow/adapters/mqtt_async.py
thingflow/adapters/pandas.py
thingflow/adapters/postgres.py
thingflow/adapters/predix.py
thingflow/adapters/tcpstreamer.py
thingflow/adapters/rpi/__init__.py
thingflow/adapters/rpi/gpio.py
thingflow/filters/__init__.py
thingflow/filters/buffer.py
thingflow/filters/combinators.py
thingflow/filters/dispatch.py
thingflow/filters/first.py
thingflow/filters/json.py
thingflow/filters/map.py
thingflow/filters/never.py
thingflow/filters/output.py
thingflow/filters/scan.py
thingflow/filters/select.py
thingflow/filters/skip.py
thingflow/filters/some.py
thingflow/filters/take.py
thingflow/filters/timeout.py
thingflow/filters/transducer.py
thingflow/filters/where.py
thingflow/internal/__init__.py
thingflow/internal/basic.py
thingflow/sensors/__init__.py
thingflow/sensors/rpi/__init__.py
thingflow/sensors/rpi/adxl345_py3.py
thingflow/sensors/rpi/arduino.py
thingflow/sensors/rpi/gpio.py
thingflow/sensors/rpi/lux_sensor.py
thingflow/sensors/rpi/sensor.py
thingflow-2.3.0.dist-info/DESCRIPTION.rst
thingflow-2.3.0.dist-info/METADATA
thingflow-2.3.0.dist-info/RECORD
thingflow-2.3.0.dist-info/WHEEL
thingflow-2.3.0.dist-info/metadata.json
thingflow-2.3.0.dist-info/top_level.txt
