Metadata-Version: 2.0
Name: thingflow
Version: 2.3.0
Summary: Event Stream processing library for IOT
Home-page: https://github.com/mpi-sws-rse/thingflow-python
Author: Jeff Fischer
Author-email: jeff+thingflow@data-ken.org
License: Apache 2.0
Keywords: events,iot,sensors
Platform: UNKNOWN
Classifier: Development Status :: 4 - Beta
Classifier: License :: OSI Approved :: Apache Software License
Classifier: Programming Language :: Python :: 3.4
Classifier: Programming Language :: Python :: 3.5
Classifier: Programming Language :: Python :: 3.6
Classifier: Operating System :: OS Independent
Classifier: Intended Audience :: Developers
